{
	"name": "Fact",
	"properties": {
		"content": {
			"query": "SELECT \n    o.DimOrdersKey,\n    c.DimCustomerKey,\n    p.DimProductKey.\n    g.DimGeographyKey,\n    f.Quantity,\n    f.UnitPrice,\n    f.TotalAmount\nFROM \n    silver.silverTable f\nLEFT JOIN\n    gold.DimOrders o ON f.OrderID = o.OrderID\nLEFT JOIN \n    gold.DimCustomer c ON f.CustomerID = c.CustomerID\nLEFT JOIN\n    gold.DimProduct p ON f.ProductID = p.ProductID\nLEFT JOIN \n    gold.DimGeography g ON f.RegionID = g.RegionID AND f.Country = g.Country",
			"metadata": {
				"language": "sql"
			},
			"currentConnection": {
				"databaseName": "salesDWH",
				"poolName": "Built-in"
			},
			"resultLimit": 5000
		},
		"type": "SqlQuery"
	}
}